bandit/__init__.py
bandit/tests.py
bandit/backends/__init__.py
bandit/backends/base.py
bandit/backends/seacuke.py
bandit/backends/smtp.py
bandit/templates/bandit/hijacked-email-header.txt
bandit/templates/bandit/hijacked-email-log-message.txt
django_email_bandit-2.0.dist-info/AUTHORS
django_email_bandit-2.0.dist-info/LICENSE.txt
django_email_bandit-2.0.dist-info/METADATA
django_email_bandit-2.0.dist-info/WHEEL
django_email_bandit-2.0.dist-info/top_level.txt
django_email_bandit-2.0.dist-info/RECORD
